<?xml version="1.0"?>
<!DOCTYPE hibernate-mapping PUBLIC "-//Hibernate/Hibernate Mapping DTD 3.0//EN"
"http://www.hibernate.org/dtd/hibernate-mapping-3.0.dtd">
<!-- Generated 1 Feb, 2015 2:24:01 PM by Hibernate Tools 3.6.0 -->
<hibernate-mapping>
    <class name="Prototypical.Requireddocuments" table="requireddocuments" catalog="ies">
        <composite-id name="id" class="Prototypical.RequireddocumentsId">
            <key-property name="jobReferenceCode" type="int">
                <column name="JobReferenceCode" />
            </key-property>
            <key-property name="requiredDocuments" type="string">
                <column name="RequiredDocuments" length="45" />
            </key-property>
        </composite-id>
    </class>
     


</hibernate-mapping>
